tendril/__init__.py
tendril_extensions_qtpl-0.1.1.dist-info/DESCRIPTION.rst
tendril_extensions_qtpl-0.1.1.dist-info/METADATA
tendril_extensions_qtpl-0.1.1.dist-info/RECORD
tendril_extensions_qtpl-0.1.1.dist-info/WHEEL
tendril_extensions_qtpl-0.1.1.dist-info/metadata.json
tendril_extensions_qtpl-0.1.1.dist-info/top_level.txt
