Metadata-Version: 2.0
Name: tendril-extensions-qtpl
Version: 0.1.1
Summary: Tendril Extensions for the QTPL Instance
Home-page: https://gitlab.com/qtpl/tendril-extensions-qtpl
Author: Chintalagiri Shashank
Author-email: shashank@chintal.in
License: AGPLv3
Keywords: tendril
Platform: UNKNOWN
Classifier: Development Status :: 4 - Beta
Classifier: Natural Language :: English
Classifier: Programming Language :: Python
